setup.cfg
setup.py
ruco/__init__.py
ruco/bits.py
ruco/cli.py
ruco/clicker.py
ruco/service.py
ruco.egg-info/PKG-INFO
ruco.egg-info/SOURCES.txt
ruco.egg-info/dependency_links.txt
ruco.egg-info/entry_points.txt
ruco.egg-info/not-zip-safe
ruco.egg-info/requires.txt
ruco.egg-info/top_level.txt