Metadata-Version: 1.1
Name: ruco
Version: 0.4
Summary: Rust (by Facepunch Studios) rcon API and shell utility
Home-page: https://github.com/nizig/ruco
Author: exo
Author-email: exo@eckso.io
License: UNKNOWN
Download-URL: https://github.com/nizig/ruco/tarball/release-0.3
Keywords: rust,rcon,game,console,facepunch
Platform: UNKNOWN
